contextualfairness/__init__.py
contextualfairness/norms.py
contextualfairness/scorer.py
contextualfairness-0.0.1.dist-info/licenses/LICENSE
contextualfairness-0.0.1.dist-info/METADATA
contextualfairness-0.0.1.dist-info/WHEEL
contextualfairness-0.0.1.dist-info/top_level.txt
contextualfairness-0.0.1.dist-info/RECORD
