Metadata-Version: 2.4
Name: contextualfairness
Version: 0.0.1
Summary: A python package for assessing machine learning fairness with multiple contextual norms.
Home-page: https://github.com/pimkerkhoven/ContextualFairness
Author: Pim Kerkhoven
Author-email: pimk@cs.umu.se
Classifier: Programming Language :: Python :: 3.10
Classifier: License :: OSI Approved :: MIT License
Classifier: Operating System :: OS Independent
Requires-Python: >=3.10.13
License-File: LICENSE
Requires-Dist: pandas==2.3.3
Requires-Dist: numpy==2.2.6
Dynamic: author
Dynamic: author-email
Dynamic: classifier
Dynamic: description
Dynamic: description-content-type
Dynamic: home-page
Dynamic: license-file
Dynamic: requires-dist
Dynamic: requires-python
Dynamic: summary
